Py_gif_converter_test_by_yeony/__init__.py
Py_gif_converter_test_by_yeony/py_converter.py
Py_gif_converter_test_by_yeony-1.0.0.dist-info/LICENSE
Py_gif_converter_test_by_yeony-1.0.0.dist-info/METADATA
Py_gif_converter_test_by_yeony-1.0.0.dist-info/WHEEL
Py_gif_converter_test_by_yeony-1.0.0.dist-info/top_level.txt
Py_gif_converter_test_by_yeony-1.0.0.dist-info/RECORD
